spidertools
