Metadata-Version: 2.1
Name: Spider-ToolsBox
Version: 0.0.4
Summary: Package For Crawler
Home-page: https://github.com/JOUUUSKA/SpiderToolBox.git
Author: JOUUUSKA
Author-email: 1393827820@qq.com
License: UNKNOWN
Platform: UNKNOWN
Classifier: Programming Language :: Python :: 3
Classifier: License :: OSI Approved :: MIT License
Classifier: Operating System :: OS Independent
Requires-Python: >=3.6
License-File: LICENSE.txt
